ioemu/__init__.py
ioemu/button.png
ioemu/demo.py
ioemu/ledoff.png
ioemu/ledon.png
ioemu/mainwindow.py
ioemu/mainwindow.ui
ioemu-0.3.4.dist-info/METADATA
ioemu-0.3.4.dist-info/WHEEL
ioemu-0.3.4.dist-info/entry_points.txt
ioemu-0.3.4.dist-info/RECORD
