Metadata-Version: 2.1
Name: ioemu
Version: 0.3.4
Summary: IO Emulator with LEDs and buttons
Home-page: https://tbs1-bo.github.io/ioemu/
License: MIT
Author: Marco Bakera
Author-email: marco@bakera.de
Requires-Python: >=3.9,<4.0
Classifier: Intended Audience :: Education
Classifier: License :: OSI Approved :: MIT License
Classifier: Operating System :: OS Independent
Classifier: Programming Language :: Python :: 3
Classifier: Programming Language :: Python :: 3.9
Classifier: Programming Language :: Python :: 3.10
Classifier: Programming Language :: Python :: 3.11
Classifier: Programming Language :: Python :: 3.12
Classifier: Topic :: Education
Classifier: Topic :: Education :: Testing
Requires-Dist: PyQt5 (>=5.11.3,<6.0.0)
Requires-Dist: setuptools (>=75.6.0,<76.0.0)
Project-URL: Repository, https://github.com/tbs1-bo/ioemu
